smugmug_downloader/__init__.py
smugmug_downloader/__main__.py
smugmug_downloader/cli.py
smugmug_downloader-0.3.1.dist-info/licenses/LICENSE
smugmug_downloader-0.3.1.dist-info/METADATA
smugmug_downloader-0.3.1.dist-info/WHEEL
smugmug_downloader-0.3.1.dist-info/entry_points.txt
smugmug_downloader-0.3.1.dist-info/top_level.txt
smugmug_downloader-0.3.1.dist-info/RECORD
