Metadata-Version: 2.4
Name: smugmug-downloader
Version: 0.3.1
Summary: Using smugmug API v2 downloads all the files stored by smugmug for a user account.
Project-URL: Homepage, https://github.com/pydanny/smugmug-downloader
Project-URL: Issues, https://github.com/pydanny/smugmug-downloader/issues
Requires-Python: >=3.14
License-File: LICENSE
Requires-Dist: requests-oauthlib>=2.0.0
Requires-Dist: rich>=14.2.0
Requires-Dist: typer>=0.21.1
Dynamic: license-file
